mqttthreaddatalogger/__init__.py
mqttthreaddatalogger/mqttthreaddatalogger.py
mqttthreaddatalogger-1.6.0.dist-info/LICENCE
mqttthreaddatalogger-1.6.0.dist-info/METADATA
mqttthreaddatalogger-1.6.0.dist-info/WHEEL
mqttthreaddatalogger-1.6.0.dist-info/top_level.txt
mqttthreaddatalogger-1.6.0.dist-info/RECORD
