Metadata-Version: 2.1
Name: mqttthreaddatalogger
Version: 1.6.0
Summary: Connexion mqtt et enregistrement des données dans un fichier csv
Author: Didier Orlandi
Author-email: didier.orlandi@wanadoo.fr
Classifier: Programming Language :: Python :: 3
Classifier: License :: OSI Approved :: MIT License
Classifier: Operating System :: OS Independent
Requires-Python: >=3.4
License-File: LICENCE
Requires-Dist: paho-mqtt
